requests_kerberos_proxy/__init__.py
requests_kerberos_proxy/adapters.py
requests_kerberos_proxy/util.py
requests_kerberos_proxy-0.1.3.dist-info/LICENSE.txt
requests_kerberos_proxy-0.1.3.dist-info/METADATA
requests_kerberos_proxy-0.1.3.dist-info/WHEEL
requests_kerberos_proxy-0.1.3.dist-info/top_level.txt
requests_kerberos_proxy-0.1.3.dist-info/RECORD
