Metadata-Version: 2.1
Name: requests-kerberos-proxy
Version: 0.1.3
Summary: Add a short description here!
Home-page: https://github.com/pyscaffold/pyscaffold/
Author: EVLT
Author-email: EVLT@cbs.nl
License: MIT
Project-URL: Documentation, https://pyscaffold.org/
Platform: any
Classifier: Development Status :: 4 - Beta
Classifier: Programming Language :: Python
License-File: LICENSE.txt
Requires-Dist: requests
Requires-Dist: requests-kerberos
Requires-Dist: urllib3
Requires-Dist: importlib-metadata ; python_version < "3.8"
Provides-Extra: dev
Requires-Dist: tox ; extra == 'dev'
Requires-Dist: black ; extra == 'dev'
Provides-Extra: testing
Requires-Dist: setuptools ; extra == 'testing'
Requires-Dist: pytest ; extra == 'testing'
Requires-Dist: pytest-cov ; extra == 'testing'
